bibas/__init__.py
bibas/extra_layouts.py
bibas/inference_utils.py
bibas/visual_analysis.py
bibas-0.2.0.dist-info/METADATA
bibas-0.2.0.dist-info/WHEEL
bibas-0.2.0.dist-info/top_level.txt
bibas-0.2.0.dist-info/RECORD
